pykindle/__init__.py
pykindle/book.py
pykindle/items.py
pykindle/readers.py
pykindle/utils/__init__.py
tests/__init__.py
tests/test_item.py
tests/test_magazine.py
tests/test_readers.py
pykindle-0.1.19.dist-info/LICENSE
pykindle-0.1.19.dist-info/METADATA
pykindle-0.1.19.dist-info/WHEEL
pykindle-0.1.19.dist-info/top_level.txt
pykindle-0.1.19.dist-info/RECORD
