Metadata-Version: 2.1
Name: pykindle
Version: 0.1.19
Summary: PyKindle: Generate mobi files in a programming way
Home-page: https://github.com/panhaoyu/pykindle
Author: Haoyu Pan
Author-email: haoyupan@aliyun.com
License: GPL
Project-URL: Documentation, https://github.com/panhaoyu/pykindle
Project-URL: Source, https://github.com/panhaoyu/pykindle
Platform: UNKNOWN
Classifier: Intended Audience :: Developers
Classifier: License :: OSI Approved :: GNU General Public License v3 (GPLv3)
Classifier: Programming Language :: Python :: 3
Classifier: Topic :: Software Development :: Libraries :: Python Modules
Requires-Dist: jinja2
Requires-Dist: markdown
